megaind/__init__.py
megaind-1.0.5.dist-info/LICENSE
megaind-1.0.5.dist-info/METADATA
megaind-1.0.5.dist-info/WHEEL
megaind-1.0.5.dist-info/top_level.txt
megaind-1.0.5.dist-info/RECORD
